taraplotlib/__init__.py
taraplotlib/py.typed
taraplotlib/assets/cat-footprint-silhouette-000000-original.svg
taraplotlib/assets/cat-silhouette-000000-original.svg
taraplotlib/assets/cup-of-tea-silhouette-000000-original.svg
taraplotlib/assets/tea-bags-silhouette-000000-original.svg
taraplotlib/examples/2d_plot.py
taraplotlib/examples/colormaps.py
taraplotlib/examples/simple_plot.py
taraplotlib/examples/single_line.py
taraplotlib/src/background.py
taraplotlib/src/colors.py
taraplotlib/src/markers.py
taraplotlib/src/py.typed
taraplotlib-1.0.0.dist-info/LICENSE
taraplotlib-1.0.0.dist-info/METADATA
taraplotlib-1.0.0.dist-info/WHEEL
taraplotlib-1.0.0.dist-info/top_level.txt
taraplotlib-1.0.0.dist-info/RECORD
