Metadata-Version: 2.1
Name: taraplotlib
Version: 1.0.0
Summary: Cosy matplotlib styles for tea and cat lovers
Author: Lorenzo Peri
License: GNU GENERAL PUBLIC LICENSE
Project-URL: Homepage, https://https://github.com/LorenzoPeri17/TaraPlotLib
Requires-Python: >=3.9
License-File: LICENSE
Requires-Dist: matplotlib
Requires-Dist: svgpath2mpl
Requires-Dist: svgpathtools
